sftpcli/__init__.py
sftpcli/main.py
sftpcli/packages/__init__.py
sftpcli/packages/core/SFTPClient.py
sftpcli/packages/core/__init__.py
sftpcli/packages/tools/__init__.py
sftpcli/packages/tools/arguments.py
sftpcli/packages/utils/__init__.py
sftpcli/packages/utils/config.py
sftpcli/packages/utils/console.py
sftpcli/packages/utils/decorations.py
sftpcli/packages/utils/normpath.py
sftpcli/packages/utils/write_config.py
sftpcli-0.0.1.dist-info/METADATA
sftpcli-0.0.1.dist-info/WHEEL
sftpcli-0.0.1.dist-info/entry_points.txt
sftpcli-0.0.1.dist-info/top_level.txt
sftpcli-0.0.1.dist-info/RECORD
