Metadata-Version: 2.4
Name: sftpcli
Version: 0.0.1
Summary: A friendly command-line SFTP client with reusable profiles.
Home-page: https://github.com/sachin-acharya-projects/sftpcli
Author: Sachin Acharya
Author-email: sftpcli.author@gmail.com
License: MIT
Classifier: Programming Language :: Python :: 3
Classifier: Operating System :: OS Independent
Requires-Python: >=3.12
Requires-Dist: paramiko
Requires-Dist: colorama
Requires-Dist: argparse
Requires-Dist: configparser
Requires-Dist: pwinput
